aixterm/__init__.py
aixterm/__main__.py
aixterm/cleanup.py
aixterm/config.py
aixterm/main.py
aixterm/mcp_client.py
aixterm/progress_display.py
aixterm/py.typed
aixterm/server.py
aixterm/utils.py
aixterm/context/__init__.py
aixterm/context/directory_handler.py
aixterm/context/log_processor.py
aixterm/context/terminal_context.py
aixterm/context/token_manager.py
aixterm/context/tool_optimizer.py
aixterm/integration/__init__.py
aixterm/integration/base.py
aixterm/integration/bash.py
aixterm/integration/fish.py
aixterm/integration/zsh.py
aixterm/llm/__init__.py
aixterm/llm/client.py
aixterm/llm/exceptions.py
aixterm/llm/message_validator.py
aixterm/llm/streaming.py
aixterm/llm/tools.py
aixterm-0.1.4.dist-info/licenses/LICENSE
aixterm-0.1.4.dist-info/METADATA
aixterm-0.1.4.dist-info/WHEEL
aixterm-0.1.4.dist-info/entry_points.txt
aixterm-0.1.4.dist-info/top_level.txt
aixterm-0.1.4.dist-info/RECORD
