Metadata-Version: 2.4
Name: aixterm
Version: 0.1.4
Summary: Terminal AI assistant with MCP support
Home-page: https://github.com/dwharve/aixterm
Author: David Harvey
Author-email: David Harvey <dwh.exis@gmail.com>
License-Expression: MIT
Project-URL: Homepage, https://github.com/dwharve/aixterm
Project-URL: Documentation, https://github.com/dwharve/aixterm/blob/main/README.md
Project-URL: Repository, https://github.com/dwharve/aixterm.git
Project-URL: Bug Tracker, https://github.com/dwharve/aixterm/issues
Keywords: ai,terminal,assistant,mcp,shell,cli
Classifier: Development Status :: 4 - Beta
Classifier: Intended Audience :: Developers
Classifier: Intended Audience :: System Administrators
Classifier: Operating System :: OS Independent
Classifier: Programming Language :: Python :: 3
Classifier: Programming Language :: Python :: 3.10
Classifier: Programming Language :: Python :: 3.11
Classifier: Programming Language :: Python :: 3.12
Classifier: Programming Language :: Python :: 3.13
Classifier: Topic :: Software Development :: Libraries :: Python Modules
Classifier: Topic :: System :: Shells
Classifier: Topic :: Utilities
Requires-Python: >=3.8
License-File: LICENSE
Requires-Dist: requests>=2.25.0
Requires-Dist: tiktoken
Requires-Dist: mcp>=1.10.0
Requires-Dist: tqdm>=4.64.0
Provides-Extra: dev
Requires-Dist: pytest>=7.0.0; extra == "dev"
Requires-Dist: pytest-cov>=4.0.0; extra == "dev"
Requires-Dist: pytest-asyncio>=0.21.0; extra == "dev"
Requires-Dist: pytest-mock>=3.10.0; extra == "dev"
Requires-Dist: black>=23.0.0; extra == "dev"
Requires-Dist: flake8>=6.0.0; extra == "dev"
Requires-Dist: mypy>=1.0.0; extra == "dev"
Requires-Dist: bandit>=1.7.0; extra == "dev"
Requires-Dist: isort>=5.0.0; extra == "dev"
Requires-Dist: pre-commit>=3.0.0; extra == "dev"
Requires-Dist: types-requests; extra == "dev"
Dynamic: author
Dynamic: home-page
Dynamic: license-file
Dynamic: requires-python
